DataSounds/__init__.py
DataSounds/sounds.py
DataSounds/editops.py
DataSounds/external/__init__.py
DataSounds/external/sebastian/LICENSE
DataSounds/external/sebastian/__init__.py
DataSounds/external/sebastian/core/transforms.py
DataSounds/external/sebastian/core/__init__.py
DataSounds/external/sebastian/core/elements.py
DataSounds/external/sebastian/core/notes.py
DataSounds/external/sebastian/lilypond/__init__.py
DataSounds/external/sebastian/lilypond/write_lilypond.py
DataSounds/external/sebastian/lilypond/interp.py
DataSounds/external/sebastian/lilypond/README
DataSounds/external/sebastian/midi/__init__.py
DataSounds/external/sebastian/midi/write_midi.py
DataSounds/external/sebastian/midi/player.py
DataSounds/external/sebastian/midi/midi.py
DataSounds/external/sebastian/midi/README
DataSounds-1.2.5.dist-info/pydist.json
DataSounds-1.2.5.dist-info/DESCRIPTION.rst
DataSounds-1.2.5.dist-info/top_level.txt
DataSounds-1.2.5.dist-info/METADATA
DataSounds-1.2.5.dist-info/WHEEL
DataSounds-1.2.5.dist-info/RECORD
