Metadata-Version: 2.0
Name: DataSounds
Version: 1.2.5
Summary: Get music from Time Series data and other sequential data.
Home-page: http://www.datasounds.org
Author: Arnaldo Russo, Luiz Irber
Author-email: arnaldo@datasounds.org, luiz@datasounds.org
License: BSD License
Keywords: Sonification Music Timeseries
Platform: any
Requires-Dist: six
Requires-Dist: numpy
